pyreload/__init__.py
pyreload/logger.py
pyreload/main.py
pyreload/monitor.py
pyreload_cli-1.0.3.dist-info/licenses/LICENSE
pyreload_cli-1.0.3.dist-info/METADATA
pyreload_cli-1.0.3.dist-info/WHEEL
pyreload_cli-1.0.3.dist-info/entry_points.txt
pyreload_cli-1.0.3.dist-info/top_level.txt
pyreload_cli-1.0.3.dist-info/RECORD
