Metadata-Version: 2.4
Name: pyreload-cli
Version: 1.0.3
Summary: Automatically restart Python applications when file changes are detected, with polling support for mounted filesystems
Author-email: dotbrains <nicholas.adamou@outlook.com>
License: MIT
Project-URL: Homepage, https://github.com/dotbrains/pyreload-cli
Project-URL: Documentation, https://dotbrains.github.io/pyreload-cli
Project-URL: Repository, https://github.com/dotbrains/pyreload-cli
Project-URL: Bug Reports, https://github.com/dotbrains/pyreload-cli/issues
Keywords: development,file-watching,hot-reload,docker,vagrant,polling,monitor,restart,devtools
Classifier: Development Status :: 4 - Beta
Classifier: Intended Audience :: Developers
Classifier: License :: OSI Approved :: MIT License
Classifier: Operating System :: OS Independent
Classifier: Programming Language :: Python :: 3
Classifier: Programming Language :: Python :: 3.8
Classifier: Programming Language :: Python :: 3.9
Classifier: Programming Language :: Python :: 3.10
Classifier: Programming Language :: Python :: 3.11
Classifier: Programming Language :: Python :: 3.12
Classifier: Topic :: Software Development
Classifier: Topic :: Software Development :: Testing
Classifier: Topic :: System :: Filesystems
Requires-Python: >=3.8
License-File: LICENSE
Requires-Dist: colorama>=0.4.4
Requires-Dist: watchdog>=2.0.0
Provides-Extra: dev
Requires-Dist: pytest>=7.0.0; extra == "dev"
Requires-Dist: pytest-cov>=4.0.0; extra == "dev"
Requires-Dist: black>=23.0.0; extra == "dev"
Requires-Dist: ruff>=0.1.0; extra == "dev"
Requires-Dist: pre-commit>=3.0.0; extra == "dev"
Dynamic: license-file
